stonetech/__init__.py
stonetech/codigo_s.py
stonetech-0.0.1.dist-info/WHEEL
stonetech-0.0.1.dist-info/METADATA
stonetech-0.0.1.dist-info/RECORD
