Metadata-Version: 2.1
Name: stonetech
Version: 0.0.1
Summary: Easter Egg to Codigo[S] - From Stone Tech
License: MIT
Author: Enderson Menezes
Author-email: endersonster@gmail.com
Requires-Python: >=3.10,<4.0
Classifier: License :: OSI Approved :: MIT License
Classifier: Programming Language :: Python :: 3
Classifier: Programming Language :: Python :: 3.10
